mutate/__init__.py
mutate/transcribe.py
mutate/lib/util.py
mutate/schema/cpu_vulnerabilities.yml
mutate/schema/dmidecode.yml
mutate/schema/yum_repos.yml
mutate/scribe_modules/__init__.py
mutate/scribe_modules/base_scribe_module.py
mutate/scribe_modules/cpu_vulnerabilities.py
mutate/scribe_modules/dmidecode.py
mutate/scribe_modules/yum_repos.py
mutate/scribe_modules/lib/util.py
mutate/scribes/__init__.py
mutate/scribes/base_scribe.py
mutate/scribes/foo.py
mutate/scribes/stockpile.py
mutate/scribes/lib/util.py
transcribe/__init__.py
transcribe/render.py
transcribe/lib/util.py
transcribe/schema/cpu_vulnerabilities.yml
transcribe/schema/dmidecode.yml
transcribe/schema/yum_repos.yml
transcribe/scribe_modules/__init__.py
transcribe/scribe_modules/base_scribe_module.py
transcribe/scribe_modules/cpu_vulnerabilities.py
transcribe/scribe_modules/dmidecode.py
transcribe/scribe_modules/yum_repos.py
transcribe/scribe_modules/lib/util.py
transcribe/scribes/__init__.py
transcribe/scribes/base_scribe.py
transcribe/scribes/foo.py
transcribe/scribes/stockpile.py
transcribe/scribes/lib/util.py
mutate-0.0.1.dev13.dist-info/LICENSE
mutate-0.0.1.dev13.dist-info/METADATA
mutate-0.0.1.dev13.dist-info/WHEEL
mutate-0.0.1.dev13.dist-info/entry_points.txt
mutate-0.0.1.dev13.dist-info/pbr.json
mutate-0.0.1.dev13.dist-info/top_level.txt
mutate-0.0.1.dev13.dist-info/RECORD
