Metadata-Version: 2.1
Name: mutate
Version: 0.0.1.dev13
Summary: Data processing tool to provide a CDM adhering readily indexable JSON docs
Home-page: https://github.com/redhat-performance/scribe
Author: redhat-performance
Author-email: browbench@redhat.com
License: UNKNOWN
Platform: UNKNOWN
Classifier: License :: OSI Approved :: Apache Software License
Classifier: Operating System :: OS Independent
Classifier: Programming Language :: Python :: 3
Requires-Dist: pyyaml (>=3.12)
Requires-Dist: argparse (>=1.4.0)
Requires-Dist: cerberus (>=1.2)
Requires-Dist: setuptools
